testarsenal.py
testarsenal-0.3.0.dist-info/DESCRIPTION.rst
testarsenal-0.3.0.dist-info/METADATA
testarsenal-0.3.0.dist-info/RECORD
testarsenal-0.3.0.dist-info/WHEEL
testarsenal-0.3.0.dist-info/metadata.json
testarsenal-0.3.0.dist-info/top_level.txt
