Metadata-Version: 2.0
Name: testarsenal
Version: 0.3.0
Summary: Testing tools
Home-page: https://github.com/samirelanduk/testarsenal
Author: Sam Ireland
Author-email: mail@samireland.com
License: MIT
Platform: UNKNOWN
Classifier: Development Status :: 4 - Beta
Classifier: Intended Audience :: Other Audience
Classifier: License :: OSI Approved :: MIT License
Classifier: Topic :: Communications
Classifier: Programming Language :: Python :: 3
Classifier: Programming Language :: Python :: 3.5
Classifier: Programming Language :: Python :: 3.6
Requires-Dist: selenium
